fixtures_generator/__init__.py
fixtures_generator/attrs_fixtures.py
fixtures_generator/attrs_fixtures_generator.py
fixtures_generator/dataclass_fixtures.py
fixtures_generator/dataclass_fixtures_generator.py
fixtures_generator/factory_fixtures.py
fixtures_generator/pydantic_fixtures.py
fixtures_generator/pydantic_fixtures_generator.py
dataclass_fixtures_generator-1.0.3.dist-info/LICENSE
dataclass_fixtures_generator-1.0.3.dist-info/METADATA
dataclass_fixtures_generator-1.0.3.dist-info/WHEEL
dataclass_fixtures_generator-1.0.3.dist-info/top_level.txt
dataclass_fixtures_generator-1.0.3.dist-info/RECORD
