Metadata-Version: 2.1
Name: dataclass-fixtures-generator
Version: 1.0.3
Summary: Fixtures generator for attrs, dataclasses and pydantic
Author-email: Pavel Shmakov <shmakovpn@yandex.ru>
License: MIT License
Project-URL: Homepage, https://github.com/shmakovpn/dataclass-fixtures-generator
Classifier: License :: OSI Approved :: MIT License
Classifier: Programming Language :: Python
Classifier: Programming Language :: Python :: 3
Requires-Python: >=3.7
License-File: LICENSE
Provides-Extra: dev
Requires-Dist: pip-tools; extra == "dev"
Requires-Dist: pytest; extra == "dev"
Requires-Dist: coverage; extra == "dev"
Requires-Dist: build; extra == "dev"
Requires-Dist: tomli; python_version < "3.11" and extra == "dev"
